load_modules/__init__.py
load_modules/load_modules.py
load_modules-0.0.1.dist-info/LICENSE
load_modules-0.0.1.dist-info/METADATA
load_modules-0.0.1.dist-info/WHEEL
load_modules-0.0.1.dist-info/top_level.txt
load_modules-0.0.1.dist-info/RECORD
