Metadata-Version: 2.1
Name: load-modules
Version: 0.0.1
Summary: Dynamically load modules from directories
Home-page: https://github.com/rhhayward/py_load_modules
Author: Ryan Hayward
Author-email: rhhayward@att.net
License: UNKNOWN
Project-URL: Bug Tracker, https://github.com/rhhayward/py_load_modules/issues
Platform: UNKNOWN
Classifier: Programming Language :: Python :: 3
Classifier: License :: OSI Approved :: MIT License
Classifier: Operating System :: OS Independent
Requires-Python: >=3.6
License-File: LICENSE
